{
    "support": [0, 1],

    "nodes": [
        [0, 0, 0],
        [5, 0, 0]
    ],

    "materials": {
        "steel": {
            "E": 2e11,
            "G": 7.6923e10
        }
    },

    "bars": [
        {
            "material": "steel",
            "A": 3.91e-3,
            "Iy": 3.891e-5,
            "Iz": 2.836e-6,
            "J": 1.295e-7,
            "nodes": [0, 1]
        }
    ],

    "loads": {
        "nodes": {
            "0": [10000, 9000, 8000, 0, 0, 0]
        }
    }
}